lydia/__init__.py
lydia/__version__.py
lydia/api_client.py
lydia/configuration.py
lydia/exceptions.py
lydia/rest.py
lydia/api/__init__.py
lydia/api/application_metadata_api.py
lydia/api/applications_api.py
lydia/api/authentication_api.py
lydia/api/domains_api.py
lydia/api/personal_authentication_tokens_api.py
lydia/api/roles_api.py
lydia/api/tokens_api.py
lydia/api/users_api.py
lydia/models/__init__.py
lydia/models/access_controlled_action.py
lydia/models/access_controlled_resource.py
lydia/models/action_id.py
lydia/models/agreement_response.py
lydia/models/api_key.py
lydia/models/authentication_information.py
lydia/models/create_api_key.py
lydia/models/create_application_request.py
lydia/models/create_domain_request.py
lydia/models/create_role_request.py
lydia/models/create_user_request.py
lydia/models/created_api_key.py
lydia/models/domain_id.py
lydia/models/domain_response.py
lydia/models/id_selector_definition.py
lydia/models/identifier_part_schema.py
lydia/models/link.py
lydia/models/lusid_problem_details.py
lydia/models/lusid_validation_problem_details.py
lydia/models/o_auth_application.py
lydia/models/problem_details.py
lydia/models/resource_list_of_access_controlled_resource.py
lydia/models/role.py
lydia/models/role_id.py
lydia/models/role_response.py
lydia/models/support_access_expiry.py
lydia/models/support_access_request.py
lydia/models/support_access_response.py
lydia/models/update_role_request.py
lydia/models/update_user_request.py
lydia/models/user_id.py
lydia/models/user_response.py
lydia/tcp/__init__.py
lydia/tcp/tcp_keep_alive_probes.py
lydia/utilities/__init__.py
lydia/utilities/api_client_builder.py
lydia/utilities/api_client_factory.py
lydia/utilities/api_configuration.py
lydia/utilities/api_configuration_loader.py
lydia/utilities/config_keys.json
lydia/utilities/lydia_retry.py
lydia/utilities/proxy_config.py
lydia/utilities/refreshing_token.py
lydia_sdk-0.0.840.dist-info/METADATA
lydia_sdk-0.0.840.dist-info/WHEEL
lydia_sdk-0.0.840.dist-info/top_level.txt
lydia_sdk-0.0.840.dist-info/RECORD
