Metadata-Version: 2.1
Name: lydia-sdk
Version: 0.0.840
Summary: Python SDK for Lydia API
Home-page: https://github.com/finbourne/lydia-sdk-python
Author: FINBOURNE Technology
Author-email: engineering@finbourne.com
License: MIT
Keywords: OpenAPI,FINBOURNE,LUSID,Lydia API
Platform: UNKNOWN
Requires-Dist: six (>=1.10)
Requires-Dist: certifi (>=14.05.14)
Requires-Dist: python-dateutil (>=2.5.3)
Requires-Dist: urllib3 (>=1.15.1)
Requires-Dist: requests (>=2.21.0)
